swot
