Metadata-Version: 2.0
Name: swot
Version: 1.0.1
Summary: Swot is a community-driven or crowdsourced library for verifying that domain names and email addresses are tied to a legitimate university of college.
Home-page: http://github.com/ze/swot
Author: Zakaria Elkatani
Author-email: zelkatani@gmail.com
License: MIT
Keywords: swot email academic university college verification identification
Platform: UNKNOWN
Classifier: Development Status :: 5 - Production/Stable
Classifier: Intended Audience :: Developers
Classifier: License :: OSI Approved :: MIT License
Classifier: Operating System :: OS Independent
Classifier: Programming Language :: Python
Classifier: Programming Language :: Python :: 3.6
Classifier: Programming Language :: Python :: 3.7
Requires-Python: >=3.6
